python_template/__init__.py
python_template/example.py
python_template_ingwersen_erik-0.1.0.dist-info/LICENSE
python_template_ingwersen_erik-0.1.0.dist-info/WHEEL
python_template_ingwersen_erik-0.1.0.dist-info/METADATA
python_template_ingwersen_erik-0.1.0.dist-info/RECORD
