Metadata-Version: 2.1
Name: python-template-ingwersen-erik
Version: 0.1.0
Summary: Repositorio template para criacao de projetos em Python.
Home-page: https://github.com/ingwersen-erik/python-template
License: MIT
Keywords: Template,Packaging,Python,Poetry
Author: ingwersen-erik
Author-email: erik.ingwersen@br.ey.com
Requires-Python: >=3.9,<4.0
Classifier: Development Status :: 3 - Alpha
Classifier: Intended Audience :: Developers
Classifier: License :: OSI Approved :: MIT License
Classifier: Operating System :: OS Independent
Classifier: Programming Language :: Python :: 3
Classifier: Programming Language :: Python :: 3 :: Only
Classifier: Programming Language :: Python :: 3.10
Classifier: Programming Language :: Python :: 3.11
Classifier: Programming Language :: Python :: 3.7
Classifier: Programming Language :: Python :: 3.8
Classifier: Programming Language :: Python :: 3.9
Classifier: Topic :: Software Development :: Libraries :: Python Modules
Requires-Dist: click (>=8.1.3,<9.0.0)
Requires-Dist: docutils (>=0.18.1,<0.19.0)
Requires-Dist: pip (>=22.0.4,<23.0.0)
Project-URL: Documentation, https://ingwersen-erik.github.io/python-template
Project-URL: Repository, https://github.com/ingwersen-erik/python-template
